smsapp/__init__.py
smsapp/admin.py
smsapp/apps.py
smsapp/exceptions.py
smsapp/forms.py
smsapp/models.py
smsapp/sms_provider.py
smsapp/tests.py
smsapp/urls.py
smsapp/utils.py
smsapp/views.py
smsapp/migrations/0001_initial.py
smsapp/migrations/0002_auto_20231008_1159.py
smsapp/migrations/0003_auto_20231008_1249.py
smsapp/migrations/0004_auto_20231009_0504.py
smsapp/migrations/0005_auto_20231011_2149.py
smsapp/migrations/__init__.py
smsapp/providers/__init__.py
smsapp/providers/africastalking_sms.py
smsapp/providers/geez_sms.py
smsapp/providers/jak_sms.py
smsapp/providers/kmi_sms.py
smsapp/templates/chart/index.html
smsapp/templates/chart/tabel.html
smsapp/templates/partials/base.html
django_sms_package-1.0.dist-info/LICENSE
django_sms_package-1.0.dist-info/METADATA
django_sms_package-1.0.dist-info/WHEEL
django_sms_package-1.0.dist-info/top_level.txt
django_sms_package-1.0.dist-info/RECORD
