Metadata-Version: 2.1
Name: django-sms-package
Version: 1.0
Summary: A Django app to conduct web-based polls.
Author: Imran Mohammed
Author-email: imo60067035@gmail.com
License: MIT
Classifier: Environment :: Web Environment
Classifier: Framework :: Django
Classifier: Intended Audience :: Developers
Classifier: License :: OSI Approved :: MIT License
Classifier: Operating System :: OS Independent
Classifier: Programming Language :: Python
Classifier: Programming Language :: Python :: 3
Classifier: Programming Language :: Python :: 3 :: Only
Classifier: Programming Language :: Python :: 3.8
Classifier: Programming Language :: Python :: 3.9
Requires-Python: >=3.8
License-File: LICENSE
Requires-Dist: Django
Requires-Dist: africastalking
Requires-Dist: requests
